zmemory/__init__.py
zmemory-0.1.3.dist-info/METADATA
zmemory-0.1.3.dist-info/WHEEL
zmemory-0.1.3.dist-info/licenses/LICENSE
zmemory-0.1.3.dist-info/RECORD
