Metadata-Version: 2.1
Name: zmemory
Version: 0.1.3
Summary: zen memory library
Project-URL: Homepage, https://github.com/inspirare6/zmemory
Project-URL: Bug Tracker, https://github.com/inspirare6/zmemory/issues
Author-email: inspirare6 <inspirare6@163.com>
License-File: LICENSE
Classifier: License :: OSI Approved :: MIT License
Classifier: Operating System :: OS Independent
Classifier: Programming Language :: Python :: 3
Requires-Python: >=3.7
Requires-Dist: redis
